README.rst
pyproject.toml
pytest_everyfunc/__init__.py
pytest_everyfunc/plugin.py
pytest_everyfunc.egg-info/PKG-INFO
pytest_everyfunc.egg-info/SOURCES.txt
pytest_everyfunc.egg-info/dependency_links.txt
pytest_everyfunc.egg-info/entry_points.txt
pytest_everyfunc.egg-info/requires.txt
pytest_everyfunc.egg-info/top_level.txt