Metadata-Version: 2.4
Name: pytest-everyfunc
Version: 0.1.3
Summary: A pytest plugin to detect completely untested functions using coverage
Author-email: Johannes Buchner <johannes.buchner.acad@gmx.com>
License-Expression: BSD-2-Clause
Project-URL: Homepage, https://github.com/JohannesBuchner/pytest-everyfunc
Project-URL: Documentation, https://github.com/JohannesBuchner/pytest-everyfunc
Project-URL: Repository, https://github.com/JohannesBuchner/pytest-everyfunc
Project-URL: Issues, https://github.com/JohannesBuchner/pytest-everyfunc/issues
Classifier: Development Status :: 4 - Beta
Classifier: Intended Audience :: Developers
Classifier: Topic :: Software Development :: Testing
Classifier: Programming Language :: Python :: 3
Classifier: Framework :: Pytest
Requires-Dist: pytest
Requires-Dist: coverage
Requires-Dist: pytest-cov
